pydicomrt/__init__.py
pydicomrt/ct/ct_ds_iod.py
pydicomrt/dose/__init__.py
pydicomrt/dose/builder.py
pydicomrt/dose/dose_ds_iod.py
pydicomrt/dose/sitk_transform.py
pydicomrt/reg/__init__.py
pydicomrt/reg/builder.py
pydicomrt/reg/check.py
pydicomrt/reg/ds_reg_ds_iod.py
pydicomrt/reg/parser.py
pydicomrt/reg/s_reg_ds_iod.py
pydicomrt/reg/type_transform.py
pydicomrt/reg/method/__init__.py
pydicomrt/reg/method/bspline.py
pydicomrt/reg/method/demons.py
pydicomrt/reg/method/rigid.py
pydicomrt/reg/method/soft_demons.py
pydicomrt/rs/__init__.py
pydicomrt/rs/add_new_roi.py
pydicomrt/rs/builder.py
pydicomrt/rs/checker.py
pydicomrt/rs/contour_process_method.py
pydicomrt/rs/make_contour_sequence.py
pydicomrt/rs/packer.py
pydicomrt/rs/parser.py
pydicomrt/rs/rs_ds_iod.py
pydicomrt/rs/rs_to_volume.py
pydicomrt/utils/__init__.py
pydicomrt/utils/coordinate_transform.py
pydicomrt/utils/image_series_loader.py
pydicomrt/utils/rs_from_altas.py
pydicomrt/utils/sitk_transform.py
pydicomrt/utils/validate_dcm_info.py
pydicomrt-0.6.4.dist-info/METADATA
pydicomrt-0.6.4.dist-info/WHEEL
pydicomrt-0.6.4.dist-info/entry_points.txt
pydicomrt-0.6.4.dist-info/licenses/LICENSE
pydicomrt-0.6.4.dist-info/RECORD
