Metadata-Version: 2.4
Name: pydicomrt
Version: 0.6.4
Summary: DICOM RT Structure and Registration
Author-email: Higumalu <higuma.lu@gmail.com>
License: MIT
License-File: LICENSE
Requires-Python: >=3.8
Requires-Dist: numpy>=1.26.4
Requires-Dist: opencv-python>=4.10.0
Requires-Dist: pydicom>=2.0.0
Requires-Dist: scipy>=1.10.3
Requires-Dist: simpleitk>=2.5.0
